recompyle/__about__.py
recompyle/__init__.py
recompyle/decorators/__init__.py
recompyle/decorators/decorate_function.py
recompyle/rewrite/__init__.py
recompyle/rewrite/rewrite_function.py
recompyle/transformers/__init__.py
recompyle/transformers/base.py
recompyle/transformers/function.py
recompyle-0.4.1.dist-info/METADATA
recompyle-0.4.1.dist-info/WHEEL
recompyle-0.4.1.dist-info/licenses/LICENSE.txt
recompyle-0.4.1.dist-info/RECORD
