Metadata-Version: 2.1
Name: recompyle
Version: 0.4.1
Summary: Tools for modifying source at runtime. Flat profiling of critical functions. Wrap all calls in a function.
Project-URL: Homepage, https://github.com/DanWehr/recompyle
Project-URL: Documentation, https://github.com/DanWehr/recompyle#readme
Project-URL: Issues, https://github.com/DanWehr/recompyle/issues
Project-URL: Repository, https://github.com/DanWehr/recompyle.git
Author-email: Daniel Wehr <danwehr@gmail.com>
License-Expression: MIT
License-File: LICENSE.txt
Classifier: Development Status :: 3 - Alpha
Classifier: Intended Audience :: Developers
Classifier: License :: OSI Approved :: MIT License
Classifier: Operating System :: OS Independent
Classifier: Programming Language :: Python :: 3
Classifier: Programming Language :: Python :: 3.10
Classifier: Programming Language :: Python :: 3.11
Classifier: Programming Language :: Python :: 3.12
Classifier: Topic :: Software Development :: Libraries :: Python Modules
Classifier: Topic :: Utilities
Requires-Python: >=3.10
